[{"date":"Mon, 27 Jun 2016 14:54:34 GMT","sloc":13,"lloc":8,"functions":1,"deliveredBugs":0.05349122917508017,"maintainability":71.68647758044561,"lintErrors":[],"difficulty":4.11764705882353},{"date":"Mon, 27 Jun 2016 14:54:53 GMT","sloc":13,"lloc":8,"functions":1,"deliveredBugs":0.05349122917508017,"maintainability":71.68647758044561,"lintErrors":[],"difficulty":4.11764705882353},{"date":"Mon, 27 Jun 2016 14:58:10 GMT","sloc":13,"lloc":8,"functions":1,"deliveredBugs":0.05349122917508017,"maintainability":71.68647758044561,"lintErrors":[],"difficulty":4.11764705882353},{"date":"Mon, 27 Jun 2016 15:03:56 GMT","sloc":13,"lloc":8,"functions":1,"deliveredBugs":0.05349122917508017,"maintainability":71.68647758044561,"lintErrors":[],"difficulty":4.11764705882353},{"date":"Mon, 27 Jun 2016 15:06:59 GMT","sloc":13,"lloc":8,"functions":1,"deliveredBugs":0.05349122917508017,"maintainability":71.68647758044561,"lintErrors":[],"difficulty":4.11764705882353},{"date":"Mon, 27 Jun 2016 15:07:23 GMT","sloc":13,"lloc":8,"functions":1,"deliveredBugs":0.05349122917508017,"maintainability":71.68647758044561,"lintErrors":[],"difficulty":4.11764705882353},{"date":"Mon, 27 Jun 2016 15:12:47 GMT","sloc":13,"lloc":8,"functions":1,"deliveredBugs":0.05349122917508017,"maintainability":71.68647758044561,"lintErrors":[],"difficulty":4.11764705882353},{"date":"Mon, 27 Jun 2016 15:19:08 GMT","sloc":13,"lloc":8,"functions":1,"deliveredBugs":0.05349122917508017,"maintainability":71.68647758044561,"lintErrors":[],"difficulty":4.11764705882353},{"date":"Mon, 27 Jun 2016 15:19:10 GMT","sloc":13,"lloc":8,"functions":1,"deliveredBugs":0.05349122917508017,"maintainability":71.68647758044561,"lintErrors":[],"difficulty":4.11764705882353},{"date":"Mon, 27 Jun 2016 15:23:46 GMT","sloc":13,"lloc":8,"functions":1,"deliveredBugs":0.05349122917508017,"maintainability":71.68647758044561,"lintErrors":[],"difficulty":4.11764705882353},{"date":"Mon, 27 Jun 2016 15:30:06 GMT","sloc":13,"lloc":8,"functions":1,"deliveredBugs":0.05349122917508017,"maintainability":71.68647758044561,"lintErrors":[],"difficulty":4.11764705882353},{"date":"Mon, 27 Jun 2016 15:30:45 GMT","sloc":13,"lloc":8,"functions":1,"deliveredBugs":0.05349122917508017,"maintainability":71.68647758044561,"lintErrors":[],"difficulty":4.11764705882353},{"date":"Mon, 27 Jun 2016 15:36:45 GMT","sloc":13,"lloc":8,"functions":1,"deliveredBugs":0.05349122917508017,"maintainability":71.68647758044561,"lintErrors":[],"difficulty":4.11764705882353},{"date":"Mon, 27 Jun 2016 15:38:29 GMT","sloc":13,"lloc":8,"functions":1,"deliveredBugs":0.05349122917508017,"maintainability":71.68647758044561,"lintErrors":[],"difficulty":4.11764705882353},{"date":"Mon, 27 Jun 2016 15:38:49 GMT","sloc":13,"lloc":8,"functions":1,"deliveredBugs":0.05349122917508017,"maintainability":71.68647758044561,"lintErrors":[],"difficulty":4.11764705882353},{"date":"Mon, 27 Jun 2016 15:39:28 GMT","sloc":13,"lloc":8,"functions":1,"deliveredBugs":0.05349122917508017,"maintainability":71.68647758044561,"lintErrors":[],"difficulty":4.11764705882353},{"date":"Mon, 27 Jun 2016 15:39:33 GMT","sloc":13,"lloc":8,"functions":1,"deliveredBugs":0.05349122917508017,"maintainability":71.68647758044561,"lintErrors":[],"difficulty":4.11764705882353},{"date":"Mon, 27 Jun 2016 15:39:48 GMT","sloc":13,"lloc":8,"functions":1,"deliveredBugs":0.05349122917508017,"maintainability":71.68647758044561,"lintErrors":[],"difficulty":4.11764705882353},{"date":"Mon, 27 Jun 2016 15:40:55 GMT","sloc":13,"lloc":8,"functions":1,"deliveredBugs":0.05349122917508017,"maintainability":71.68647758044561,"lintErrors":[],"difficulty":4.11764705882353},{"date":"Mon, 27 Jun 2016 15:41:04 GMT","sloc":13,"lloc":8,"functions":1,"deliveredBugs":0.05349122917508017,"maintainability":71.68647758044561,"lintErrors":[],"difficulty":4.11764705882353},{"date":"Mon, 27 Jun 2016 15:41:45 GMT","sloc":13,"lloc":8,"functions":1,"deliveredBugs":0.05349122917508017,"maintainability":71.68647758044561,"lintErrors":[],"difficulty":4.11764705882353},{"date":"Mon, 27 Jun 2016 15:42:04 GMT","sloc":13,"lloc":8,"functions":1,"deliveredBugs":0.05349122917508017,"maintainability":71.68647758044561,"lintErrors":[],"difficulty":4.11764705882353},{"date":"Mon, 27 Jun 2016 15:42:09 GMT","sloc":13,"lloc":8,"functions":1,"deliveredBugs":0.05349122917508017,"maintainability":71.68647758044561,"lintErrors":[],"difficulty":4.11764705882353},{"date":"Mon, 27 Jun 2016 15:42:17 GMT","sloc":13,"lloc":8,"functions":1,"deliveredBugs":0.05349122917508017,"maintainability":71.68647758044561,"lintErrors":[],"difficulty":4.11764705882353},{"date":"Mon, 27 Jun 2016 15:42:20 GMT","sloc":13,"lloc":8,"functions":1,"deliveredBugs":0.05349122917508017,"maintainability":71.68647758044561,"lintErrors":[],"difficulty":4.11764705882353},{"date":"Mon, 27 Jun 2016 15:42:49 GMT","sloc":13,"lloc":8,"functions":1,"deliveredBugs":0.05349122917508017,"maintainability":71.68647758044561,"lintErrors":[],"difficulty":4.11764705882353},{"date":"Mon, 27 Jun 2016 15:45:54 GMT","sloc":13,"lloc":8,"functions":1,"deliveredBugs":0.05349122917508017,"maintainability":71.68647758044561,"lintErrors":[],"difficulty":4.11764705882353},{"date":"Mon, 27 Jun 2016 15:48:46 GMT","sloc":13,"lloc":8,"functions":1,"deliveredBugs":0.05349122917508017,"maintainability":71.68647758044561,"lintErrors":[],"difficulty":4.11764705882353},{"date":"Mon, 27 Jun 2016 15:48:52 GMT","sloc":13,"lloc":8,"functions":1,"deliveredBugs":0.05349122917508017,"maintainability":71.68647758044561,"lintErrors":[],"difficulty":4.11764705882353},{"date":"Mon, 27 Jun 2016 15:48:56 GMT","sloc":13,"lloc":8,"functions":1,"deliveredBugs":0.05349122917508017,"maintainability":71.68647758044561,"lintErrors":[],"difficulty":4.11764705882353},{"date":"Mon, 27 Jun 2016 15:49:12 GMT","sloc":13,"lloc":8,"functions":1,"deliveredBugs":0.05349122917508017,"maintainability":71.68647758044561,"lintErrors":[],"difficulty":4.11764705882353},{"date":"Mon, 27 Jun 2016 15:49:15 GMT","sloc":13,"lloc":8,"functions":1,"deliveredBugs":0.05349122917508017,"maintainability":71.68647758044561,"lintErrors":[],"difficulty":4.11764705882353},{"date":"Mon, 27 Jun 2016 15:49:40 GMT","sloc":13,"lloc":8,"functions":1,"deliveredBugs":0.05349122917508017,"maintainability":71.68647758044561,"lintErrors":[],"difficulty":4.11764705882353},{"date":"Mon, 27 Jun 2016 15:50:24 GMT","sloc":13,"lloc":8,"functions":1,"deliveredBugs":0.05349122917508017,"maintainability":71.68647758044561,"lintErrors":[],"difficulty":4.11764705882353},{"date":"Mon, 27 Jun 2016 15:50:37 GMT","sloc":13,"lloc":8,"functions":1,"deliveredBugs":0.05349122917508017,"maintainability":71.68647758044561,"lintErrors":[],"difficulty":4.11764705882353},{"date":"Mon, 27 Jun 2016 15:50:42 GMT","sloc":13,"lloc":8,"functions":1,"deliveredBugs":0.05349122917508017,"maintainability":71.68647758044561,"lintErrors":[],"difficulty":4.11764705882353},{"date":"Mon, 27 Jun 2016 15:50:51 GMT","sloc":13,"lloc":8,"functions":1,"deliveredBugs":0.05349122917508017,"maintainability":71.68647758044561,"lintErrors":[],"difficulty":4.11764705882353},{"date":"Mon, 27 Jun 2016 15:51:37 GMT","sloc":13,"lloc":8,"functions":1,"deliveredBugs":0.05349122917508017,"maintainability":71.68647758044561,"lintErrors":[],"difficulty":4.11764705882353},{"date":"Mon, 27 Jun 2016 15:52:06 GMT","sloc":13,"lloc":8,"functions":1,"deliveredBugs":0.05349122917508017,"maintainability":71.68647758044561,"lintErrors":[],"difficulty":4.11764705882353},{"date":"Mon, 27 Jun 2016 15:53:58 GMT","sloc":13,"lloc":8,"functions":1,"deliveredBugs":0.05349122917508017,"maintainability":71.68647758044561,"lintErrors":[],"difficulty":4.11764705882353},{"date":"Mon, 27 Jun 2016 15:54:51 GMT","sloc":13,"lloc":8,"functions":1,"deliveredBugs":0.05349122917508017,"maintainability":71.68647758044561,"lintErrors":[],"difficulty":4.11764705882353},{"date":"Mon, 27 Jun 2016 15:55:08 GMT","sloc":13,"lloc":8,"functions":1,"deliveredBugs":0.05349122917508017,"maintainability":71.68647758044561,"lintErrors":[],"difficulty":4.11764705882353},{"date":"Mon, 27 Jun 2016 15:59:19 GMT","sloc":13,"lloc":8,"functions":1,"deliveredBugs":0.05349122917508017,"maintainability":71.68647758044561,"lintErrors":[],"difficulty":4.11764705882353},{"date":"Mon, 27 Jun 2016 15:59:29 GMT","sloc":13,"lloc":8,"functions":1,"deliveredBugs":0.05349122917508017,"maintainability":71.68647758044561,"lintErrors":[],"difficulty":4.11764705882353},{"date":"Mon, 27 Jun 2016 16:00:23 GMT","sloc":13,"lloc":8,"functions":1,"deliveredBugs":0.05349122917508017,"maintainability":71.68647758044561,"lintErrors":[],"difficulty":4.11764705882353},{"date":"Mon, 27 Jun 2016 16:00:31 GMT","sloc":13,"lloc":8,"functions":1,"deliveredBugs":0.05349122917508017,"maintainability":71.68647758044561,"lintErrors":[],"difficulty":4.11764705882353},{"date":"Mon, 27 Jun 2016 16:01:32 GMT","sloc":13,"lloc":8,"functions":1,"deliveredBugs":0.05349122917508017,"maintainability":71.68647758044561,"lintErrors":[],"difficulty":4.11764705882353},{"date":"Mon, 27 Jun 2016 16:01:57 GMT","sloc":13,"lloc":8,"functions":1,"deliveredBugs":0.05349122917508017,"maintainability":71.68647758044561,"lintErrors":[],"difficulty":4.11764705882353},{"date":"Mon, 27 Jun 2016 16:02:17 GMT","sloc":13,"lloc":8,"functions":1,"deliveredBugs":0.05349122917508017,"maintainability":71.68647758044561,"lintErrors":[],"difficulty":4.11764705882353},{"date":"Mon, 27 Jun 2016 16:02:20 GMT","sloc":13,"lloc":8,"functions":1,"deliveredBugs":0.05349122917508017,"maintainability":71.68647758044561,"lintErrors":[],"difficulty":4.11764705882353},{"date":"Mon, 27 Jun 2016 16:02:50 GMT","sloc":13,"lloc":8,"functions":1,"deliveredBugs":0.05349122917508017,"maintainability":71.68647758044561,"lintErrors":[],"difficulty":4.11764705882353},{"date":"Mon, 27 Jun 2016 16:03:46 GMT","sloc":13,"lloc":8,"functions":1,"deliveredBugs":0.05349122917508017,"maintainability":71.68647758044561,"lintErrors":[],"difficulty":4.11764705882353}]